topsis/__init__.py
topsis/__main__.py
Topsis_Karansingla_102003355-1.0.0.dist-info/License.txt
Topsis_Karansingla_102003355-1.0.0.dist-info/METADATA
Topsis_Karansingla_102003355-1.0.0.dist-info/WHEEL
Topsis_Karansingla_102003355-1.0.0.dist-info/entry_points.txt
Topsis_Karansingla_102003355-1.0.0.dist-info/top_level.txt
Topsis_Karansingla_102003355-1.0.0.dist-info/RECORD
