Metadata-Version: 2.1
Name: Topsis-Karansingla-102003355
Version: 1.0.0
Summary: A Python package implementing TOPSIS technique.
Home-page: 
Author: karan singla
Author-email: karansingla2123@gmail.com
License: MIT
Classifier: License :: OSI Approved :: MIT License
Classifier: Programming Language :: Python :: 3
Classifier: Programming Language :: Python :: 3.7
License-File: License.txt
Requires-Dist: numpy
Requires-Dist: pandas
